[
    {
        "actionName": "Action",
        "steps": [
            {
                "stepId": "STEP1162",
                "stepName": "Url: WebTours",
                "infFile": "t2.inf",
                "time": 1658522605758
            },
            {
                "stepId": "STEP1163",
                "stepName": "Submit Data: login.pl",
                "infFile": "t3.inf",
                "time": 1658522608325
            },
            {
                "stepId": "STEP1164",
                "stepName": "Url: Search Flights Button",
                "infFile": "t4.inf",
                "time": 1658522610994
            },
            {
                "stepId": "STEP1165",
                "stepName": "Submit Data: reservations.pl",
                "infFile": "t7.inf",
                "time": 1658522613626
            },
            {
                "stepId": "STEP1166",
                "stepName": "Submit Data: reservations.pl_2",
                "infFile": "t8.inf",
                "time": 1658522616239
            },
            {
                "stepId": "STEP1167",
                "stepName": "Submit Data: reservations.pl_3",
                "infFile": "t9.inf",
                "time": 1658522618842
            }
        ],
        "transactions": [
            {
                "transactionName": "homepage",
                "rawStartTime": 1658522603223,
                "rawEndTime": 1658522605759,
                "thinkTime": 0.0,
                "wastedTime": 2.3638336658477785
            },
            {
                "transactionName": "login",
                "rawStartTime": 1658522605774,
                "rawEndTime": 1658522608327,
                "thinkTime": 0.0,
                "wastedTime": 2.3608949184417726
            },
            {
                "transactionName": "flights",
                "rawStartTime": 1658522608342,
                "rawEndTime": 1658522611003,
                "thinkTime": 0.0,
                "wastedTime": 2.365386486053467
            },
            {
                "transactionName": "find_flight",
                "rawStartTime": 1658522611018,
                "rawEndTime": 1658522613628,
                "thinkTime": 0.0,
                "wastedTime": 2.4139413833618166
            },
            {
                "transactionName": "select_flight",
                "rawStartTime": 1658522613644,
                "rawEndTime": 1658522616244,
                "thinkTime": 0.0,
                "wastedTime": 2.413391590118408
            },
            {
                "transactionName": "payment_details",
                "rawStartTime": 1658522616258,
                "rawEndTime": 1658522618844,
                "thinkTime": 0.0,
                "wastedTime": 2.3959994316101076
            },
            {
                "transactionName": "UC01_BuyTicket",
                "rawStartTime": 1658522603204,
                "rawEndTime": 1658522618904,
                "thinkTime": 0.0,
                "wastedTime": 14.31344747543335
            }
        ]
    }
]